manim_utils/__init__.py
manim_utils/data_scene.py
manim_utils/manim_to_pixel.py
manim_utils/matplotlib_to_manim.py
manim_utils/new_image_mobject.py
manim_utils/new_svg_mobject.py
manim_utils/new_table.py
manim_utils/scatter_plot.py
manim_utils-0.1.0.dist-info/entry_points.txt
manim_utils-0.1.0.dist-info/METADATA
manim_utils-0.1.0.dist-info/WHEEL
manim_utils-0.1.0.dist-info/RECORD
