Metadata-Version: 2.1
Name: manim-utils
Version: 0.1.0
Summary: 
Author: MathItYT
Author-email: benjamin.ubilla@uc.cl
Requires-Python: >=3.10,<3.13
Classifier: Programming Language :: Python :: 3
Classifier: Programming Language :: Python :: 3.10
Classifier: Programming Language :: Python :: 3.11
Classifier: Programming Language :: Python :: 3.12
Provides-Extra: data-science
Requires-Dist: manim (>=0.18.0,<0.19.0)
Requires-Dist: matplotlib (>=3.8.2) ; extra == "data-science"
Requires-Dist: pandas (>=2.1.3) ; extra == "data-science"
Requires-Dist: setuptools (>=69.0.2)
